{"botAcilis_":1718809278329,"custom_command_nasıl":"Discord botu için kurulması gereken programlar: https://www.youtube.com/watch?v=V0EmjTv5ho4&t","modlogK_1234857155274739793":"1250066478687060039","custom_command_website":"https://oktaydev.com.tr","modlogK_1243189595051397142":"1248669328581328916","Mod_1243189595051397142":{"guild":"1243189595051397142","icon":null,"unicodeEmoji":null,"id":"1248669317600641025","name":"Mod","color":1271764,"hoist":false,"rawPosition":8,"permissions":"10242","managed":false,"mentionable":false,"flags":0,"tags":null,"createdTimestamp":1717776364470},"Mute_1243189595051397142":{"guild":"1243189595051397142","icon":null,"unicodeEmoji":null,"id":"1248669327830286406","name":"Mute","color":8881027,"hoist":false,"rawPosition":1,"permissions":"4194304","managed":false,"mentionable":false,"flags":0,"tags":null,"createdTimestamp":1717776366909},"Jail_1243189595051397142":{"guild":"1243189595051397142","icon":null,"unicodeEmoji":null,"id":"1248669327830286406","name":"Mute","color":8881027,"hoist":false,"rawPosition":1,"permissions":"4194304","managed":false,"mentionable":false,"flags":0,"tags":null,"createdTimestamp":1717776366909},"logChannel_1243189595051397142":"1248669328581328916","1243189595051397142":{"937454716315664384":1}}